{
"type": "FeatureCollection",
"name": "Kilburn_1_structure_centroids",
"features": [
{ "type": "Feature", "properties": { "fid": 1, "id": null, "type": "mens_bathroom" }, "geometry": { "type": "Point", "coordinates": [ -2.233481397207132, 53.467349733591782 ] } },
{ "type": "Feature", "properties": { "fid": 2, "id": null, "type": "womens_bathroom" }, "geometry": { "type": "Point", "coordinates": [ -2.233530303456865, 53.467376710569575 ] } },
{ "type": "Feature", "properties": { "fid": 3, "id": null, "type": "accessible_bathroom" }, "geometry": { "type": "Point", "coordinates": [ -2.233513123009719, 53.467395907429484 ] } },
{ "type": "Feature", "properties": { "fid": 4, "id": null, "type": "lift" }, "geometry": { "type": "Point", "coordinates": [ -2.233607142561128, 53.467300989698529 ] } },
{ "type": "Feature", "properties": { "fid": 5, "id": null, "type": "stairs" }, "geometry": { "type": "Point", "coordinates": [ -2.233652005885991, 53.467298983771428 ] } },
{ "type": "Feature", "properties": { "fid": 6, "id": null, "type": "exit" }, "geometry": { "type": "Point", "coordinates": [ -2.233641214474127, 53.467276862985258 ] } },
{ "type": "Feature", "properties": { "fid": 7, "id": null, "type": "stairs" }, "geometry": { "type": "Point", "coordinates": [ -2.23339747429348, 53.467386352779599 ] } },
{ "type": "Feature", "properties": { "fid": 8, "id": null, "type": "stairs" }, "geometry": { "type": "Point", "coordinates": [ -2.233312292886024, 53.467380664342627 ] } },
{ "type": "Feature", "properties": { "fid": 9, "id": null, "type": "stairs" }, "geometry": { "type": "Point", "coordinates": [ -2.234232241284609, 53.46760480361781 ] } },
{ "type": "Feature", "properties": { "fid": 10, "id": null, "type": "accessible_lift" }, "geometry": { "type": "Point", "coordinates": [ -2.233986833779752, 53.467698810457911 ] } },
{ "type": "Feature", "properties": { "fid": 11, "id": null, "type": "stairs" }, "geometry": { "type": "Point", "coordinates": [ -2.233979337143876, 53.467718925736079 ] } },
{ "type": "Feature", "properties": { "fid": 12, "id": null, "type": "stairs" }, "geometry": { "type": "Point", "coordinates": [ -2.233925009850714, 53.467735589595641 ] } },
{ "type": "Feature", "properties": { "fid": 13, "id": null, "type": "stairs" }, "geometry": { "type": "Point", "coordinates": [ -2.233853256544724, 53.467730279681682 ] } },
{ "type": "Feature", "properties": { "fid": 14, "id": null, "type": "stairs" }, "geometry": { "type": "Point", "coordinates": [ -2.233875628369721, 53.467690921384261 ] } },
{ "type": "Feature", "properties": { "fid": 15, "id": null, "type": "exit" }, "geometry": { "type": "Point", "coordinates": [ -2.234158111142856, 53.467763132267287 ] } },
{ "type": "Feature", "properties": { "fid": 16, "id": null, "type": "exit" }, "geometry": { "type": "Point", "coordinates": [ -2.23335897291472, 53.467344118129269 ] } },
{ "type": "Feature", "properties": { "fid": 17, "id": null, "type": "exit" }, "geometry": { "type": "Point", "coordinates": [ -2.233514506764451, 53.467814407347085 ] } },
{ "type": "Feature", "properties": { "fid": 18, "id": null, "type": "stairs" }, "geometry": { "type": "Point", "coordinates": [ -2.233937061652914, 53.467702593872623 ] } }
]
}
